demonproto_x/__init__.py
demonproto_x/demon.py
demonproto_x-2.5.dist-info/METADATA
demonproto_x-2.5.dist-info/WHEEL
demonproto_x-2.5.dist-info/top_level.txt
demonproto_x-2.5.dist-info/RECORD
