Metadata-Version: 2.2
Name: demonproto_x
Version: 2.5
Summary: End-to-end encryption chat protocol
Home-page: https://github.com/certikpolik1/thecryptoxprotox
Author: ALfisene Keita
Author-email: info@infopeklo.cz
Requires-Dist: cryptography
Requires-Dist: pynacl
Dynamic: author
Dynamic: author-email
Dynamic: description
Dynamic: description-content-type
Dynamic: home-page
Dynamic: requires-dist
Dynamic: summary
